kanpai/Kanpai.py
kanpai/__init__.py
kanpai/array.py
kanpai/boolean.py
kanpai/email.py
kanpai/number.py
kanpai/object.py
kanpai/string.py
kanpai/uuid.py
kanpai/validator.py
kanpai-0.1.15.dist-info/LICENSE
kanpai-0.1.15.dist-info/METADATA
kanpai-0.1.15.dist-info/WHEEL
kanpai-0.1.15.dist-info/top_level.txt
kanpai-0.1.15.dist-info/RECORD
