Metadata-Version: 2.1
Name: kanpai
Version: 0.1.15
Summary: Python JSON schema validator with better error message
Home-page: https://github.com/chandrakantap/kanpai
Author: Chandrakanta Pal
Author-email: pal.chandrakanta@gmail.com
License: UNKNOWN
Keywords: schema json validation request-validation input-validation
Platform: UNKNOWN
Classifier: Programming Language :: Python :: 3
Classifier: License :: OSI Approved :: MIT License
Classifier: Operating System :: OS Independent
